minimappers2-0.1.7.dist-info/METADATA
minimappers2-0.1.7.dist-info/WHEEL
minimappers2-0.1.7.dist-info/licenses/LICENSE
minimappers2/__init__.py
minimappers2/minimappers2.abi3.so
minimappers2-0.1.7.dist-info/RECORD
