Metadata-Version: 2.4
Name: minimappers2
Version: 0.1.7
Classifier: Development Status :: 3 - Alpha
Classifier: Topic :: Scientific/Engineering :: Bio-Informatics
Classifier: License :: OSI Approved :: Apache Software License
Classifier: License :: OSI Approved :: MIT License
Classifier: Operating System :: POSIX :: Linux
Classifier: Programming Language :: Rust
Requires-Dist: polars >=1.19.0
Requires-Dist: pyarrow >=18.1.0
License-File: LICENSE
Summary: A Python wrapper for minimap2-rs
Keywords: minimap2,bioinformatics,alignment,mapping
Requires-Python: >=3.7
Project-URL: homepage, https://github.com/jguhlin/minimap2-rs
Project-URL: repository, https://github.com/jguhlin/minimap2-rs
